gstatsim.py
gstatsim-1.1.5.dist-info/licenses/LICENSE
gstatsim-1.1.5.dist-info/METADATA
gstatsim-1.1.5.dist-info/WHEEL
gstatsim-1.1.5.dist-info/top_level.txt
gstatsim-1.1.5.dist-info/RECORD
