Metadata-Version: 2.4
Name: gstatsim
Version: 1.1.5
Summary: Geostatistics tools for interpolation and simulation.
Home-page: https://github.com/GatorGlaciology/GStatSim
Author: (Emma) Mickey MacKie
Author-email: emackie@ufl.edu
License: MIT
Classifier: Programming Language :: Python :: 3
Classifier: License :: OSI Approved :: MIT License
Classifier: Operating System :: OS Independent
Classifier: Topic :: Scientific/Engineering :: Information Analysis
Requires-Python: >=3
License-File: LICENSE
Requires-Dist: numpy>=1.14.5
Requires-Dist: pandas>=1.1.1
Requires-Dist: scipy>=1.1.1
Requires-Dist: tqdm>=3
Requires-Dist: scikit-learn>=1.1.2
Dynamic: author
Dynamic: author-email
Dynamic: classifier
Dynamic: description
Dynamic: description-content-type
Dynamic: home-page
Dynamic: license
Dynamic: license-file
Dynamic: requires-dist
Dynamic: requires-python
Dynamic: summary
